.gitignore
.travis.yml
LICENSE
README.rst
requirements.in
requirements.txt
requirements_test.in
requirements_test.txt
setup.cfg
setup.py
doc/Makefile
doc/source/api.rst
doc/source/conf.py
doc/source/index.rst
src/pyotelem/__init__.py
src/pyotelem/_version.py
src/pyotelem/dives.py
src/pyotelem/dsp.py
src/pyotelem/dtag.py
src/pyotelem/dynamics.py
src/pyotelem/glides.py
src/pyotelem/physio_seal.py
src/pyotelem/seawater.py
src/pyotelem/utils.py
src/pyotelem.egg-info/PKG-INFO
src/pyotelem.egg-info/SOURCES.txt
src/pyotelem.egg-info/dependency_links.txt
src/pyotelem.egg-info/requires.txt
src/pyotelem.egg-info/top_level.txt
src/pyotelem.egg-info/zip-safe
src/pyotelem/plots/__init__.py
src/pyotelem/plots/plotconfig.py
src/pyotelem/plots/plotdives.py
src/pyotelem/plots/plotdsp.py
src/pyotelem/plots/plotdynamics.py
src/pyotelem/plots/plotglides.py
src/pyotelem/plots/plotutils.py
tests/pylleo/test_utils.py